pydbus/__init__.py
pydbus/_inspect3.py
pydbus/auto_names.py
pydbus/bus.py
pydbus/bus_names.py
pydbus/context.py
pydbus/exitable.py
pydbus/generic.py
pydbus/identifier.py
pydbus/proxy.py
pydbus/proxy_method.py
pydbus/proxy_property.py
pydbus/proxy_signal.py
pydbus/publication.py
pydbus/registration.py
pydbus/subscription.py
pydbus/examples/__init__.py
pydbus/examples/systemctl.py
pydbus/examples/clientserver/__init__.py
pydbus/examples/clientserver/client.py
pydbus/examples/clientserver/server.py
pydbus/tests/__init__.py
pydbus/tests/context.py
pydbus/tests/expose.py
pydbus/tests/expose_multiface.py
pydbus/tests/gnome_music.py
pydbus/tests/identifier.py
pydbus/tests/publish.py
pydbus/tests/publish_multiface.py
pydbus-0.5.1.dist-info/DESCRIPTION.rst
pydbus-0.5.1.dist-info/METADATA
pydbus-0.5.1.dist-info/RECORD
pydbus-0.5.1.dist-info/WHEEL
pydbus-0.5.1.dist-info/metadata.json
pydbus-0.5.1.dist-info/top_level.txt
pydbus-0.5.1.dist-info/zip-safe
