Metadata-Version: 2.0
Name: pydbus
Version: 0.5.1
Summary: Pythonic DBus library
Home-page: https://github.com/LEW21/pydbus
Author: Janusz Lewandowski
Author-email: lew21@xtreeme.org
License: LGPLv2+
Keywords: dbus
Platform: UNKNOWN
Classifier: Development Status :: 5 - Production/Stable
Classifier: Intended Audience :: Developers
Classifier: Natural Language :: English
Classifier: License :: OSI Approved :: GNU Lesser General Public License v2 or later (LGPLv2+)
Classifier: Programming Language :: Python
Classifier: Programming Language :: Python :: 3
Classifier: Programming Language :: Python :: 3.3
Classifier: Programming Language :: Python :: 3.4
Classifier: Programming Language :: Python :: 3.5
Classifier: Programming Language :: Python :: 2
Classifier: Programming Language :: Python :: 2.7
